{
    "address": "test.php",
    "method":"post",
    "items":[
        {
            "supertype":"text",
            "type":"text",
            "label":"First Name:",
            "attributes":
            {
                "name":"firstname",
                "id":"firstname",
                "placeholder":"John"
            }
        },
        {
            "supertype":"text",
            "type":"text",
            "label":"Last Name:",
            "attributes":
            {
                "name":"lastname",
                "id":"lastname",
                "placeholder":"Smith"
            }
        },
        {
            "supertype":"choice",
            "type":"radio",
            "label": "Gender:",
            "name":"gender",
            "options":[
                {
                    "value": "male",
                    "label": "Male"
                },
                {
                    "value": "female",
                    "label": "Female"  
                },
                {
                    "value": "other",
                    "label": "Other"
                }
            ]
        },
        {
            "supertype":"text",
            "type":"text",
            "label": "Username:",
            "attributes":
            {
                "name":"username",
                "id":"username",
                "placeholder": "Username"
            }
        },
        {
            "supertype":"text",
            "type":"password",
            "label": "Password:",
            "attributes":
            {
                "name":"pwrd",
                "id":"pwrd",
                "placeholder": "Password"
            }
        },
        {
            "supertype":"text",
            "type":"email",
            "label": "Email:",
            "attributes":
            {
                "name":"email",
                "id":"email",
                "placeholder": "Eamil"
            }
        },
        {
            "supertype":"text",
            "type":"date",
            "label": "Date:",
            "attributes":
            {
                "name":"date",
                "id":"date"
            }
        },
        {
            "supertype":"text",
            "type":"datetime-local",
            "label": "DateTime:",
            "attributes":
            {
                "name":"datetime",
                "id":"datetime"
            }
        }
    ]
}